setup.py
esdk_obs_python7666.egg-info/PKG-INFO
esdk_obs_python7666.egg-info/SOURCES.txt
esdk_obs_python7666.egg-info/dependency_links.txt
esdk_obs_python7666.egg-info/not-zip-safe
esdk_obs_python7666.egg-info/top_level.txt
obs/__init__.py
obs/auth.py
obs/bucket.py
obs/bulktasks.py
obs/cache.py
obs/client.py
obs/const.py
obs/convertor.py
obs/extension.py
obs/http2.py
obs/ilog.py
obs/loadtoken.py
obs/locks.py
obs/model.py
obs/progress.py
obs/searchmethod.py
obs/transfer.py
obs/util.py
obs/workflow.py