Metadata-Version: 1.0
Name: esdk-obs-python7666
Version: 3.20.11
Summary: OBS Python SDK
Home-page: UNKNOWN
Author: UNKNOWN
Author-email: UNKNOWN
License: Apache-2.0
Platform: Independant
